[
  {
    "title": "UFC 伦敦赛结果：埃夫洛耶夫 VS 墨菲",
    "url": "https://www.ufc.com/news/ufc-london-results-evloev-vs-murphy-main-card-highlights-winners-interviews",
    "industry": "The Official Website of the Ultimate Fighting Championship",
    "summary": "UFC 格斗之夜：埃夫洛耶夫 vs 墨菲于 2026 年 3 月 21 日在伦敦 O2 举行的现场赛果、精彩集锦和赛后采访。",
    "charlotte_impact": "提供 UFC 主要赛事的实时更新和见解，对体育迷有吸引力。",
    "impact_score": 3
  },
  {
    "title": "特朗普将在国土安全部关闭期间部署移民代理",
    "url": "https://www.nbcnews.com/news/us-news/trump-threatens-send-federal-immigration-agents-airports-dhs-shutdown-rcna264467",
    "industry": "NBC News",
    "summary": "由于国土安全部的资金僵局，特朗普总统计划派遣 ICE 特工前往机场。",
    "charlotte_impact": "强调了正在进行的移民问题政治斗争及其对国家安全的潜在影响。",
    "impact_score": 4
  },
  {
    "title": "前联邦调查局局长罗伯特·穆勒去世，享年 81 岁",
    "url": "https://www.aljazeera.com/news/2026/3/21/former-fbi-chief-robert-mueller-dead-at-81",
    "industry": "Al Jazeera English",
    "summary": "主导调查俄罗斯干预 2016 年美国大选的罗伯特·穆勒 (Robert Mueller) 去世，享年 81 岁。",
    "charlotte_impact": "标志着美国近代政治史上一位关键人物的去世和一项有争议的调查。",
    "impact_score": 4
  },
  {
    "title": "在哈梅内伊的猜测中，伊朗的权力转移有利于伊斯兰革命卫队",
    "url": "https://www.jpost.com/israel-news/article-890716",
    "industry": "The Jerusalem Post",
    "summary": "随着革命卫队 (IRGC) 在伊朗获得影响力，人们对莫吉塔巴·哈梅内伊的角色进行了猜测。",
    "charlotte_impact": "表明伊朗政权内部权力动态可能发生变化，影响地区稳定。",
    "impact_score": 3
  },
  {
    "title": "《巴菲》演员向尼古拉斯·布兰登致敬",
    "url": "http://www.hollywoodreporter.com/tv/tv-news/nicholas-brendon-dead-buffy-vampire-slayer-tributes-1236543178/",
    "industry": "Hollywood Reporter",
    "summary": "《吸血鬼猎人巴菲》的演员们还记得尼古拉斯·布兰登，他在睡梦中因自然原因去世。",
    "charlotte_impact": "强调了布伦登工作的影响以及粉丝和同事的集体哀悼。",
    "impact_score": 3
  },
  {
    "title": "特朗普团队规划潜在的伊朗和谈",
    "url": "https://www.axios.com/2026/03/21/trump-peace-deal-iran-kushner-witkoff",
    "industry": "Axios",
    "summary": "据报道，白宫正在探索与伊朗进行和平谈判的途径。",
    "charlotte_impact": "表明美国对伊朗的外交政策可能发生转变，从而可能缓解紧张局势。",
    "impact_score": 3
  },
  {
    "title": "夏威夷面临严重洪水，数千人撤离",
    "url": "https://www.bbc.com/news/articles/c20qj970gwro",
    "industry": "BBC News",
    "summary": "夏威夷遭遇 20 年来最严重的洪水，已有 230 多人获救。",
    "charlotte_impact": "说明气候变化的影响日益增加以及备灾的必要性。",
    "impact_score": 4
  },
  {
    "title": "BTS 的“阿里郎”回归服装：设计师的愿景",
    "url": "http://wwd.com/fashion-news/fashion-features/bts-arirang-comeback-costumes-jay-songzio-lyrical-armor-1238685143/",
    "industry": "WWD",
    "summary": "看看 Jay Songzio 制作的防弹少年团“阿里郎”复出服装，将韩国传统与现代时尚融为一体。",
    "charlotte_impact": "在备受期待的表演中展示文化与时尚的融合。",
    "impact_score": 3
  },
  {
    "title": "疯狂三月：周六 NCAA 锦标赛排名",
    "url": "https://www.usatoday.com/story/sports/ncaab/2026/03/21/march-madness-schedule-today-ncaa-tournament-second-round/89234521007/",
    "industry": "USA Today",
    "summary": "2026 年 NCAA 锦标赛八场第二轮男子疯狂三月比赛的排名和细分。",
    "charlotte_impact": "为球迷提供 NCAA 篮球锦标赛的见解和预测。",
    "impact_score": 3
  },
  {
    "title": "美国军方：伊朗对霍尔木兹海峡的控制“退化”",
    "url": "https://www.cnn.com/world/live-news/iran-war-us-israel-trump-03-21-26",
    "industry": "CNN",
    "summary": "弹道导弹向美英迪戈加西亚基地发射，引发了人们对伊朗军事行动的担忧。",
    "charlotte_impact": "强调中东紧张局势不断升级以及对国际安全的潜在威胁。",
    "impact_score": 4
  },
  {
    "title": "WNBA 协议包含独特的“怀孕条款”",
    "url": "https://www.outkick.com/culture/wild-pregnancy-clause-included-new-wnba-deal",
    "industry": "Outkick.com",
    "summary": "WNBA 的一份新合同包含一项与怀孕相关的不寻常合同条款。",
    "charlotte_impact": "提请注意职业体育合同的具体劳动条件和独特方面。",
    "impact_score": 3
  },
  {
    "title": "特朗普在伊朗问题上引用珍珠港事件后，日本感到不安",
    "url": "https://www.aljazeera.com/news/2026/3/21/unease-in-japan-after-trump-uses-pearl-harbor-to-defend-iran-war",
    "industry": "Al Jazeera English",
    "summary": "特朗普引用珍珠港事件来捍卫伊朗战争，引起了日本的不安，日本首相高市的沉默反应不一。",
    "charlotte_impact": "说明围绕历史事件和当前地缘政治紧张局势的外交敏感性。",
    "impact_score": 3
  },
  {
    "title": "国会寻求特朗普退出伊朗战争的计划",
    "url": "https://apnews.com/article/iran-war-powers-exit-strategy-congress-trump-781ef538fbb493cf0973c6a89698f36e",
    "industry": "Associated Press",
    "summary": "议员们正在质疑与伊朗的战争的持续时间和成本，寻求特朗普总统的退出战略。",
    "charlotte_impact": "反映出人们对持续冲突日益增长的担忧以及明确解决方案的必要性。",
    "impact_score": 4
  },
  {
    "title": "苹果收购 Halide 的尝试引发诉讼",
    "url": "https://www.macrumors.com/2026/03/21/apple-wanted-to-buy-halide-to-boost-iphone-18-pro/",
    "industry": "MacRumors",
    "summary": "苹果计划收购 Halide 以改进 iPhone 18 Pro 的相机应用程序失败，导致诉讼。",
    "charlotte_impact": "揭示技术收购的竞争格局和潜在的法律纠纷。",
    "impact_score": 3
  },
  {
    "title": "特朗普在直播中得知查克·诺里斯去世的消息",
    "url": "https://www.mediaite.com/media/news/oh-he-did-trump-finds-out-chuck-norris-died-live-on-air-from-reporter-hours-after-news-broke/",
    "industry": "Mediaite",
    "summary": "特朗普总统在镜头前的闲聊中从一名记者获悉查克·诺里斯的死讯。",
    "charlotte_impact": "强调新闻传播的实时性以及公众对名人去世的反应。",
    "impact_score": 3
  }
]